zenmoney_api/__init__.py
zenmoney_api/auth.py
zenmoney_api/client.py
zenmoney_api/models.py
zenmoney_api/py.typed
zenmoney_api-0.1.0a5.dist-info/METADATA
zenmoney_api-0.1.0a5.dist-info/WHEEL
zenmoney_api-0.1.0a5.dist-info/licenses/LICENSE
zenmoney_api-0.1.0a5.dist-info/RECORD
