Metadata-Version: 2.4
Name: zenmoney-api
Version: 0.1.0a5
Summary: Zenmoney API client
Author-email: Konstantin Sazhenov <me@sakost.dev>
License: MIT License
License-File: LICENSE
Classifier: Development Status :: 2 - Pre-Alpha
Classifier: Intended Audience :: Developers
Classifier: License :: OSI Approved :: MIT License
Classifier: Operating System :: OS Independent
Classifier: Programming Language :: Python :: 3
Classifier: Programming Language :: Python :: 3.12
Classifier: Programming Language :: Python :: 3.13
Classifier: Programming Language :: Python :: Implementation :: CPython
Classifier: Programming Language :: Python :: Implementation :: PyPy
Classifier: Topic :: Office/Business :: Financial :: Accounting
Requires-Python: >=3.12
Requires-Dist: authlib>=1.6.1
Requires-Dist: httpx[brotli,http2,zstd]>=0.28.1
Requires-Dist: pydantic>=2.11.7
Requires-Dist: uvloop>=0.21.0; sys_platform != 'win32'
